scam_shield_utils/__init__.py
scam_shield_utils/aws_operations.py
scam_shield_utils/data_opeations.py
scam_shield_utils/logger_log.py
scam_shield_utils/postgres_connector.py
scam_shield_utils-1.0.6.dist-info/LICENSE
scam_shield_utils-1.0.6.dist-info/METADATA
scam_shield_utils-1.0.6.dist-info/WHEEL
scam_shield_utils-1.0.6.dist-info/top_level.txt
scam_shield_utils-1.0.6.dist-info/RECORD
