Metadata-Version: 2.1
Name: scam_shield_utils
Version: 1.0.6
Summary: Utility Package for Scamshield Solution
Author-email: Naveen <naveenmk@outlook.com>
Project-URL: Homepage, https://gitlab.com/mnf-group/scamshield-group/scamshield-utils
Project-URL: Issues, https://gitlab.com/mnf-group/scamshield-group/scamshield-utils/issues
Classifier: Programming Language :: Python :: 3
Classifier: License :: OSI Approved :: MIT License
Classifier: Operating System :: OS Independent
Requires-Python: >=3.8
License-File: LICENSE
